[
  {
    "title": "btv",
    "updated": "2026-01-26T21:45:59.046Z",
    "url": "https://ipstream.xyz:8443/hls/btv/playlist.m3u8?e=1769467556&st=f--9Vew-r1BP9sjERo6YzQ",
    "headers": "Referer: https://gledaibgtv.com/\nUser-Agent: Mozilla/5.0 (Windows NT 10.0; Win64; x64) AppleWebKit/537.36 (KHTML, like Gecko) Chrome/139.0.0.0 Safari/537.36"
  },
  {
    "title": "nova-tv",
    "updated": "2026-01-26T21:46:02.811Z",
    "url": "https://tmstream.xyz:34443/hls/novatv/playlist.m3u8?e=1769471160&st=Q27Hlc4zocuFVqojwn5JLA",
    "headers": "Referer: https://tvmaniabg.com/\nUser-Agent: Mozilla/5.0 (Windows NT 10.0; Win64; x64) AppleWebKit/537.36 (KHTML, like Gecko) Chrome/139.0.0.0 Safari/537.36"
  },
  {
    "title": "bnt1",
    "updated": "2026-01-26T21:46:06.204Z",
    "url": "https://tmstream.xyz:34443/hls/bnt1/playlist.m3u8?e=1769471164&st=0SB4dnxufqKkODSeC8E2iA",
    "headers": "Referer: https://tvmaniabg.com/\nUser-Agent: Mozilla/5.0 (Windows NT 10.0; Win64; x64) AppleWebKit/537.36 (KHTML, like Gecko) Chrome/139.0.0.0 Safari/537.36\nOrigin: https://tvmaniabg.com"
  }
]