[
  {
    "title": "btv",
    "updated": "2026-01-07T13:52:39.198Z",
    "url": "https://ipstream.xyz:8443/hls/btv/playlist.m3u8?e=1767797556&st=zuiCjxrIVbFEWRGmB-3nmw",
    "headers": "Referer: https://gledaibgtv.com/\nUser-Agent: Mozilla/5.0 (Windows NT 10.0; Win64; x64) AppleWebKit/537.36 (KHTML, like Gecko) Chrome/139.0.0.0 Safari/537.36"
  },
  {
    "title": "nova-tv",
    "updated": "2026-01-07T13:52:42.918Z",
    "url": "https://tmstream.xyz:34443/hls/novatv/playlist.m3u8?e=1767801160&st=vJBeqQONQqYHr5O4CqoIRw",
    "headers": "Referer: https://tvmaniabg.com/\nUser-Agent: Mozilla/5.0 (Windows NT 10.0; Win64; x64) AppleWebKit/537.36 (KHTML, like Gecko) Chrome/139.0.0.0 Safari/537.36"
  },
  {
    "title": "bnt1",
    "updated": "2026-01-07T13:52:46.207Z",
    "url": "https://tmstream.xyz:34443/hls/bnt1/playlist.m3u8?e=1767801164&st=UEcx0Gsrqo4kOXOjTTl6Fw",
    "headers": "Referer: https://tvmaniabg.com/\nUser-Agent: Mozilla/5.0 (Windows NT 10.0; Win64; x64) AppleWebKit/537.36 (KHTML, like Gecko) Chrome/139.0.0.0 Safari/537.36\nOrigin: https://tvmaniabg.com"
  },
  {
    "title": "mtv-00s-live-tv",
    "updated": "2026-01-07T13:52:51.755Z",
    "url": "https://cdn.stgledai.org:8082/hls/mtv00s/index.m3u8?token=eecc802d84c67591872382d31c333ab5d7346e88-00e26317e451bc9e726365598591d237-1767804467-1767793667",
    "headers": "Referer: https://cdn.gledaitv.fan/\nUser-Agent: Mozilla/5.0 (Windows NT 10.0; Win64; x64) AppleWebKit/537.36 (KHTML, like Gecko) Chrome/139.0.0.0 Safari/537.36"
  },
  {
    "title": "mtv-hits-live-tv",
    "updated": "2026-01-07T13:52:57.290Z",
    "url": "https://cdn.stgledai.org:8082/hls/mtvhits/index.m3u8?token=f468d781f3ae82665a7ddbbb0836c3dc125b878d-4f30b5ea3c7c1c4347295d2d378d2fec-1767804473-1767793673",
    "headers": "Referer: https://cdn.gledaitv.fan/\nUser-Agent: Mozilla/5.0 (Windows NT 10.0; Win64; x64) AppleWebKit/537.36 (KHTML, like Gecko) Chrome/139.0.0.0 Safari/537.36\nOrigin: https://cdn.gledaitv.fan"
  }
]