[
  {
    "title": "btv",
    "updated": "2026-04-08T11:44:50.872Z",
    "url": "https://aistr.xyz:28791/hls/btv/playlist.m3u8?e=1775652288&st=FONkDIxh9C93IAQz6vMHow",
    "headers": "Referer: https://gledaibgtv.com/\nUser-Agent: Mozilla/5.0 (Windows NT 10.0; Win64; x64) AppleWebKit/537.36 (KHTML, like Gecko) Chrome/139.0.0.0 Safari/537.36"
  },
  {
    "title": "nova-tv",
    "updated": "2026-04-08T11:44:55.071Z",
    "url": "https://aistr.xyz:28791/hls/novatv/playlist.m3u8?e=1775652292&st=ZMhTSCOa0MEQXdHMSGZSpA",
    "headers": "Referer: https://tvmaniabg.com/\nUser-Agent: Mozilla/5.0 (Windows NT 10.0; Win64; x64) AppleWebKit/537.36 (KHTML, like Gecko) Chrome/139.0.0.0 Safari/537.36"
  },
  {
    "title": "bnt1",
    "updated": "2026-04-08T11:44:58.645Z",
    "url": "https://aistr.xyz:28791/hls/bnt1/playlist.m3u8?e=1775652296&st=cn0-Xuzim9k2kSYiD83cBQ",
    "headers": "Referer: https://tvmaniabg.com/\nUser-Agent: Mozilla/5.0 (Windows NT 10.0; Win64; x64) AppleWebKit/537.36 (KHTML, like Gecko) Chrome/139.0.0.0 Safari/537.36\nOrigin: https://tvmaniabg.com"
  }
]